yuvio/__init__.py
yuvio/core/__init__.py
yuvio/core/colorspace.py
yuvio/core/format.py
yuvio/core/functions.py
yuvio/core/reader.py
yuvio/core/writer.py
yuvio/core/yuv.py
yuvio/formats/__init__.py
yuvio/formats/gray.py
yuvio/formats/nv12.py
yuvio/formats/v210.py
yuvio/formats/yuv420i.py
yuvio/formats/yuv420p.py
yuvio/formats/yuv422i.py
yuvio/formats/yuv422p.py
yuvio/formats/yuv444i.py
yuvio/formats/yuv444p.py
yuvio/formats/yuyv422.py
yuvio-1.6.dist-info/licenses/LICENSE
yuvio-1.6.dist-info/METADATA
yuvio-1.6.dist-info/WHEEL
yuvio-1.6.dist-info/top_level.txt
yuvio-1.6.dist-info/RECORD
