Metadata-Version: 2.4
Name: yuvio
Version: 1.6
Summary: Read and write uncompressed yuv/ycbcr image and video files
Home-page: https://github.com/labradon/yuvio
Author: Andy Regensky
Author-email: info@andyregensky.dev
Project-URL: Bug Tracker, https://github.com/labradon/yuvio/issues
Classifier: Programming Language :: Python :: 3
Classifier: Programming Language :: Python :: 3.6
Classifier: Programming Language :: Python :: 3.7
Classifier: Programming Language :: Python :: 3.8
Classifier: Programming Language :: Python :: 3.9
Classifier: Programming Language :: Python :: 3.10
Classifier: Programming Language :: Python :: 3.11
Classifier: Programming Language :: Python :: 3.12
Classifier: Programming Language :: Python :: 3.13
Classifier: License :: OSI Approved :: MIT License
Classifier: Operating System :: OS Independent
Classifier: Intended Audience :: Science/Research
Classifier: Intended Audience :: Education
Classifier: Intended Audience :: Developers
Requires-Python: >=3.6
License-File: LICENSE
Requires-Dist: numpy
Requires-Dist: psutil
Dynamic: license-file
